README.md
setup.py
cuishuang/__init__.py
cuishuang/print_shuangge_handsome.py
cuishuang.egg-info/PKG-INFO
cuishuang.egg-info/SOURCES.txt
cuishuang.egg-info/dependency_links.txt
cuishuang.egg-info/top_level.txt